pymotifcounter/__init__.py
pymotifcounter/abstractcounter.py
pymotifcounter/concretecounters.py
pymotifcounter/counter_fanmod.py
pymotifcounter/counter_mfinder.py
pymotifcounter/counter_netmode.py
pymotifcounter/counter_pgd.py
pymotifcounter/exceptions.py
pymotifcounter/parameters.py
pymotifcounter/util.py
pymotifcounter/validators.py
pymotifcounter-1.0.1.data/data/bin/NetMODE
pymotifcounter-1.0.1.data/data/bin/fanmod_cmd
pymotifcounter-1.0.1.data/data/bin/mfinder
pymotifcounter-1.0.1.data/data/bin/pgd
pymotifcounter-1.0.1.dist-info/LICENSE
pymotifcounter-1.0.1.dist-info/METADATA
pymotifcounter-1.0.1.dist-info/WHEEL
pymotifcounter-1.0.1.dist-info/top_level.txt
pymotifcounter-1.0.1.dist-info/zip-safe
pymotifcounter-1.0.1.dist-info/RECORD
