Metadata-Version: 2.1
Name: pymotifcounter
Version: 1.0.1
Summary: A simple wrapper for graph motif counting algorithms
Home-page: https://github.com/aanastasiou/pymotifcounter
Author: Athanasios Anastasiou
Author-email: athanastasiou@gmail.com
License: Apache License 2.0
Keywords: networks,graph theory,mathematics,graphlets,motifs,graph,discrete mathematics,math
Platform: UNKNOWN
Classifier: Development Status :: 4 - Beta
Classifier: Topic :: Scientific/Engineering
Classifier: Topic :: Scientific/Engineering :: Bio-Informatics
Classifier: Topic :: Scientific/Engineering :: Mathematics
Classifier: Topic :: Scientific/Engineering :: Information Analysis
Classifier: Topic :: Scientific/Engineering :: Physics
Classifier: Topic :: Software Development :: Libraries :: Python Modules
Classifier: Operating System :: POSIX :: Linux
Classifier: License :: OSI Approved :: Apache Software License
Classifier: Intended Audience :: Developers
Classifier: Intended Audience :: Science/Research
Classifier: Natural Language :: English
Classifier: Programming Language :: Python :: 3
License-File: LICENSE
Requires-Dist: pandas
Requires-Dist: networkx
Requires-Dist: pyparsing
